odoo/addons/edi_sale_edifact_oca/README.rst
odoo/addons/edi_sale_edifact_oca/__init__.py
odoo/addons/edi_sale_edifact_oca/__manifest__.py
odoo/addons/edi_sale_edifact_oca/demo/edi_exchange_type.xml
odoo/addons/edi_sale_edifact_oca/i18n/edi_sale_edifact_oca.pot
odoo/addons/edi_sale_edifact_oca/i18n/it.po
odoo/addons/edi_sale_edifact_oca/readme/CONTRIBUTORS.rst
odoo/addons/edi_sale_edifact_oca/readme/DESCRIPTION.rst
odoo/addons/edi_sale_edifact_oca/static/description/icon.png
odoo/addons/edi_sale_edifact_oca/static/description/index.html
odoo/addons/edi_sale_edifact_oca/tests/__init__.py
odoo/addons/edi_sale_edifact_oca/tests/common.py
odoo/addons/edi_sale_edifact_oca/tests/test_order.py
odoo_addon_edi_sale_edifact_oca-16.0.1.1.0.1.dist-info/METADATA
odoo_addon_edi_sale_edifact_oca-16.0.1.1.0.1.dist-info/WHEEL
odoo_addon_edi_sale_edifact_oca-16.0.1.1.0.1.dist-info/top_level.txt
odoo_addon_edi_sale_edifact_oca-16.0.1.1.0.1.dist-info/RECORD
