Metadata-Version: 2.1
Name: odoo-addon-edi-sale-edifact-oca
Version: 16.0.1.1.0.1
Summary: Provide a demo exchange type setting and common tests for EDIFACT standard in EDI on sales.
Home-page: https://github.com/OCA/edi-framework
Author: Camptocamp,Odoo Community Association (OCA)
Author-email: support@odoo-community.org
License: AGPL-3
Platform: UNKNOWN
Classifier: Programming Language :: Python
Classifier: Framework :: Odoo
Classifier: Framework :: Odoo :: 16.0
Classifier: License :: OSI Approved :: GNU Affero General Public License v3
Classifier: Development Status :: 3 - Alpha
Requires-Python: >=3.10
Requires-Dist: odoo-addon-edi-edifact-oca <16.1dev,>=16.0dev
Requires-Dist: odoo-addon-edi-sale-oca <16.1dev,>=16.0dev
Requires-Dist: odoo-addon-sale-order-import-edifact <16.1dev,>=16.0dev
Requires-Dist: odoo <16.1dev,>=16.0a
